erp_sync/__init__.py
erp_sync/admin.py
erp_sync/apps.py
erp_sync/models.py
erp_sync/APIs/__init__.py
erp_sync/APIs/api_format.py
erp_sync/APIs/utils/__init__.py
erp_sync/APIs/utils/generate_code.py
erp_sync/Clients/__init__.py
erp_sync/Clients/client.py
erp_sync/Media/__init__.py
erp_sync/Media/Uploads/__init__.py
erp_sync/Media/Uploads/Statements/__init__.py
erp_sync/Nash/__init__.py
erp_sync/Nash/nash.py
erp_sync/Resources/__init__.py
erp_sync/Resources/bank_accounts.py
erp_sync/Resources/bank_transactions.py
erp_sync/Resources/bank_transfers.py
erp_sync/Resources/banks.py
erp_sync/Resources/bill_invoices.py
erp_sync/Resources/bill_payments.py
erp_sync/Resources/chart_of_accounts.py
erp_sync/Resources/client_types.py
erp_sync/Resources/clients.py
erp_sync/Resources/company.py
erp_sync/Resources/currencies.py
erp_sync/Resources/customer.py
erp_sync/Resources/invoices.py
erp_sync/Resources/items.py
erp_sync/Resources/operations.py
erp_sync/Resources/payments.py
erp_sync/Resources/records.py
erp_sync/Resources/resource.py
erp_sync/Resources/taxes.py
erp_sync/Resources/uploads.py
erp_sync/Resources/users.py
erp_sync/Resources/vendor_payments.py
erp_sync/Resources/vendors.py
erp_sync/middlewares/__init__.py
erp_sync/middlewares/logs.py
erp_sync/migrations/0001_initial.py
erp_sync/migrations/__init__.py
nashledger-0.0.87.dist-info/LICENSE
nashledger-0.0.87.dist-info/METADATA
nashledger-0.0.87.dist-info/WHEEL
nashledger-0.0.87.dist-info/top_level.txt
nashledger-0.0.87.dist-info/RECORD
