Metadata-Version: 2.1
Name: nashledger
Version: 0.0.87
Summary: Python library for connecting to the Nash E.R.P. Framework
Home-page: https://github.com/NashInc/NashSync.git
Author: Dansol Obondo
Author-email: dansol@nashafrica.co
License: UNKNOWN
Platform: UNKNOWN
Classifier: Programming Language :: Python :: 3
Classifier: Programming Language :: Python :: 3.6
Classifier: Programming Language :: Python :: 3.7
Classifier: License :: OSI Approved :: MIT License
Classifier: Operating System :: OS Independent
License-File: LICENSE
